tft/aug.py
tft/mdct.py
tft/models.py
tft/transforms.py
tft/utils.py
tft/wavelet.py
tft-0.13.0.dist-info/METADATA
tft-0.13.0.dist-info/WHEEL
tft-0.13.0.dist-info/top_level.txt
tft-0.13.0.dist-info/RECORD
