Metadata-Version: 2.2
Name: tft
Version: 0.13.0
Summary: Time-Frequency Transformers
Author-email: Dan Jacobellis <danjacobellis@utexas.edu>
Classifier: Programming Language :: Python :: 3
Classifier: Operating System :: OS Independent
Requires-Python: >=3.6
Requires-Dist: torch
Requires-Dist: einops
Requires-Dist: PyWavelets
Requires-Dist: torchvision
